{
    "task1": {
        "input": {},
        "name": "Chart Classification",
        "output": {
            "chart_type": "line"
        }
    },
    "task2": {
        "input": {
            "task1_output": {
                "chart_type": "line"
            }
        },
        "name": "Text Detection and Recognition",
        "output": {
            "text_blocks": [
                {
                    "id": 0,
                    "polygon": {
                        "x0": 550,
                        "x1": 582,
                        "x2": 582,
                        "x3": 550,
                        "y0": 37,
                        "y1": 37,
                        "y2": 62,
                        "y3": 62
                    },
                    "text": "K_{to}"
                },
                {
                    "id": 1,
                    "polygon": {
                        "x0": 550,
                        "x1": 562,
                        "x2": 562,
                        "x3": 550,
                        "y0": 65,
                        "y1": 65,
                        "y2": 85,
                        "y3": 85
                    },
                    "text": "3"
                },
                {
                    "id": 2,
                    "polygon": {
                        "x0": 550,
                        "x1": 581,
                        "x2": 581,
                        "x3": 550,
                        "y0": 95,
                        "y1": 95,
                        "y2": 115,
                        "y3": 115
                    },
                    "text": "2.8"
                },
                {
                    "id": 3,
                    "polygon": {
                        "x0": 550,
                        "x1": 580,
                        "x2": 580,
                        "x3": 550,
                        "y0": 126,
                        "y1": 126,
                        "y2": 146,
                        "y3": 146
                    },
                    "text": "2.5"
                },
                {
                    "id": 4,
                    "polygon": {
                        "x0": 663,
                        "x1": 692,
                        "x2": 692,
                        "x3": 663,
                        "y0": 380,
                        "y1": 380,
                        "y2": 400,
                        "y3": 400
                    },
                    "text": "0.5"
                },
                {
                    "id": 5,
                    "polygon": {
                        "x0": 551,
                        "x1": 581,
                        "x2": 581,
                        "x3": 551,
                        "y0": 380,
                        "y1": 380,
                        "y2": 400,
                        "y3": 400
                    },
                    "text": "0.4"
                },
                {
                    "id": 6,
                    "polygon": {
                        "x0": 440,
                        "x1": 470,
                        "x2": 470,
                        "x3": 440,
                        "y0": 380,
                        "y1": 380,
                        "y2": 400,
                        "y3": 400
                    },
                    "text": "0.3"
                },
                {
                    "id": 7,
                    "polygon": {
                        "x0": 328,
                        "x1": 358,
                        "x2": 358,
                        "x3": 328,
                        "y0": 380,
                        "y1": 380,
                        "y2": 400,
                        "y3": 400
                    },
                    "text": "0.2"
                },
                {
                    "id": 8,
                    "polygon": {
                        "x0": 217,
                        "x1": 245,
                        "x2": 245,
                        "x3": 217,
                        "y0": 380,
                        "y1": 380,
                        "y2": 400,
                        "y3": 400
                    },
                    "text": "0.1"
                },
                {
                    "id": 9,
                    "polygon": {
                        "x0": 63,
                        "x1": 94,
                        "x2": 94,
                        "x3": 63,
                        "y0": 344,
                        "y1": 344,
                        "y2": 364,
                        "y3": 364
                    },
                    "text": "0.0"
                },
                {
                    "id": 10,
                    "polygon": {
                        "x0": 63,
                        "x1": 95,
                        "x2": 95,
                        "x3": 63,
                        "y0": 3,
                        "y1": 3,
                        "y2": 21,
                        "y3": 21
                    },
                    "text": "4.0"
                },
                {
                    "id": 11,
                    "polygon": {
                        "x0": 63,
                        "x1": 93,
                        "x2": 93,
                        "x3": 63,
                        "y0": 87,
                        "y1": 87,
                        "y2": 107,
                        "y3": 107
                    },
                    "text": "3.0"
                },
                {
                    "id": 12,
                    "polygon": {
                        "x0": 63,
                        "x1": 95,
                        "x2": 95,
                        "x3": 63,
                        "y0": 173,
                        "y1": 173,
                        "y2": 193,
                        "y3": 193
                    },
                    "text": "2.0"
                },
                {
                    "id": 13,
                    "polygon": {
                        "x0": 67,
                        "x1": 95,
                        "x2": 95,
                        "x3": 67,
                        "y0": 258,
                        "y1": 258,
                        "y2": 278,
                        "y3": 278
                    },
                    "text": "1.0"
                },
                {
                    "id": 14,
                    "polygon": {
                        "x0": 115,
                        "x1": 128,
                        "x2": 128,
                        "x3": 115,
                        "y0": 380,
                        "y1": 380,
                        "y2": 400,
                        "y3": 400
                    },
                    "text": "0"
                },
                {
                    "id": 15,
                    "polygon": {
                        "x0": 364,
                        "x1": 437,
                        "x2": 437,
                        "x3": 364,
                        "y0": 423,
                        "y1": 423,
                        "y2": 452,
                        "y3": 452
                    },
                    "text": "S_{h}/2S_{c}"
                },
                {
                    "id": 16,
                    "polygon": {
                        "x0": 3,
                        "x1": 34,
                        "x2": 34,
                        "x3": 3,
                        "y0": 25,
                        "y1": 25,
                        "y2": 346,
                        "y3": 346
                    },
                    "text": "NC(\\Delta\\sigma)^{3}/ (a_i^0.5 - a_f^-0.5) (10^{-2})"
                }
            ]
        }
    },
    "task3": {
        "input": {
            "task1_output": {
                "chart_type": "line"
            },
            "task2_output": {
                "text_blocks": [
                    {
                        "id": 0,
                        "polygon": {
                            "x0": 550,
                            "x1": 582,
                            "x2": 582,
                            "x3": 550,
                            "y0": 37,
                            "y1": 37,
                            "y2": 62,
                            "y3": 62
                        },
                        "text": "K_{to}"
                    },
                    {
                        "id": 1,
                        "polygon": {
                            "x0": 550,
                            "x1": 562,
                            "x2": 562,
                            "x3": 550,
                            "y0": 65,
                            "y1": 65,
                            "y2": 85,
                            "y3": 85
                        },
                        "text": "3"
                    },
                    {
                        "id": 2,
                        "polygon": {
                            "x0": 550,
                            "x1": 581,
                            "x2": 581,
                            "x3": 550,
                            "y0": 95,
                            "y1": 95,
                            "y2": 115,
                            "y3": 115
                        },
                        "text": "2.8"
                    },
                    {
                        "id": 3,
                        "polygon": {
                            "x0": 550,
                            "x1": 580,
                            "x2": 580,
                            "x3": 550,
                            "y0": 126,
                            "y1": 126,
                            "y2": 146,
                            "y3": 146
                        },
                        "text": "2.5"
                    },
                    {
                        "id": 4,
                        "polygon": {
                            "x0": 663,
                            "x1": 692,
                            "x2": 692,
                            "x3": 663,
                            "y0": 380,
                            "y1": 380,
                            "y2": 400,
                            "y3": 400
                        },
                        "text": "0.5"
                    },
                    {
                        "id": 5,
                        "polygon": {
                            "x0": 551,
                            "x1": 581,
                            "x2": 581,
                            "x3": 551,
                            "y0": 380,
                            "y1": 380,
                            "y2": 400,
                            "y3": 400
                        },
                        "text": "0.4"
                    },
                    {
                        "id": 6,
                        "polygon": {
                            "x0": 440,
                            "x1": 470,
                            "x2": 470,
                            "x3": 440,
                            "y0": 380,
                            "y1": 380,
                            "y2": 400,
                            "y3": 400
                        },
                        "text": "0.3"
                    },
                    {
                        "id": 7,
                        "polygon": {
                            "x0": 328,
                            "x1": 358,
                            "x2": 358,
                            "x3": 328,
                            "y0": 380,
                            "y1": 380,
                            "y2": 400,
                            "y3": 400
                        },
                        "text": "0.2"
                    },
                    {
                        "id": 8,
                        "polygon": {
                            "x0": 217,
                            "x1": 245,
                            "x2": 245,
                            "x3": 217,
                            "y0": 380,
                            "y1": 380,
                            "y2": 400,
                            "y3": 400
                        },
                        "text": "0.1"
                    },
                    {
                        "id": 9,
                        "polygon": {
                            "x0": 63,
                            "x1": 94,
                            "x2": 94,
                            "x3": 63,
                            "y0": 344,
                            "y1": 344,
                            "y2": 364,
                            "y3": 364
                        },
                        "text": "0.0"
                    },
                    {
                        "id": 10,
                        "polygon": {
                            "x0": 63,
                            "x1": 95,
                            "x2": 95,
                            "x3": 63,
                            "y0": 3,
                            "y1": 3,
                            "y2": 21,
                            "y3": 21
                        },
                        "text": "4.0"
                    },
                    {
                        "id": 11,
                        "polygon": {
                            "x0": 63,
                            "x1": 93,
                            "x2": 93,
                            "x3": 63,
                            "y0": 87,
                            "y1": 87,
                            "y2": 107,
                            "y3": 107
                        },
                        "text": "3.0"
                    },
                    {
                        "id": 12,
                        "polygon": {
                            "x0": 63,
                            "x1": 95,
                            "x2": 95,
                            "x3": 63,
                            "y0": 173,
                            "y1": 173,
                            "y2": 193,
                            "y3": 193
                        },
                        "text": "2.0"
                    },
                    {
                        "id": 13,
                        "polygon": {
                            "x0": 67,
                            "x1": 95,
                            "x2": 95,
                            "x3": 67,
                            "y0": 258,
                            "y1": 258,
                            "y2": 278,
                            "y3": 278
                        },
                        "text": "1.0"
                    },
                    {
                        "id": 14,
                        "polygon": {
                            "x0": 115,
                            "x1": 128,
                            "x2": 128,
                            "x3": 115,
                            "y0": 380,
                            "y1": 380,
                            "y2": 400,
                            "y3": 400
                        },
                        "text": "0"
                    },
                    {
                        "id": 15,
                        "polygon": {
                            "x0": 364,
                            "x1": 437,
                            "x2": 437,
                            "x3": 364,
                            "y0": 423,
                            "y1": 423,
                            "y2": 452,
                            "y3": 452
                        },
                        "text": "S_{h}/2S_{c}"
                    },
                    {
                        "id": 16,
                        "polygon": {
                            "x0": 3,
                            "x1": 34,
                            "x2": 34,
                            "x3": 3,
                            "y0": 25,
                            "y1": 25,
                            "y2": 346,
                            "y3": 346
                        },
                        "text": "NC(\\Delta\\sigma)^{3}/ (a_i^0.5 - a_f^-0.5) (10^{-2})"
                    }
                ]
            }
        },
        "name": "Text Role Classification",
        "output": {
            "text_roles": [
                {
                    "id": 0,
                    "role": "legend_title"
                },
                {
                    "id": 1,
                    "role": "legend_label"
                },
                {
                    "id": 2,
                    "role": "legend_label"
                },
                {
                    "id": 3,
                    "role": "legend_label"
                },
                {
                    "id": 4,
                    "role": "tick_label"
                },
                {
                    "id": 5,
                    "role": "tick_label"
                },
                {
                    "id": 6,
                    "role": "tick_label"
                },
                {
                    "id": 7,
                    "role": "tick_label"
                },
                {
                    "id": 8,
                    "role": "tick_label"
                },
                {
                    "id": 9,
                    "role": "tick_label"
                },
                {
                    "id": 10,
                    "role": "tick_label"
                },
                {
                    "id": 11,
                    "role": "tick_label"
                },
                {
                    "id": 12,
                    "role": "tick_label"
                },
                {
                    "id": 13,
                    "role": "tick_label"
                },
                {
                    "id": 14,
                    "role": "tick_label"
                },
                {
                    "id": 15,
                    "role": "axis_title"
                },
                {
                    "id": 16,
                    "role": "axis_title"
                }
            ]
        }
    },
    "task4": {
        "input": {
            "task1_output": {
                "chart_type": "line"
            },
            "task2_output": {
                "text_blocks": [
                    {
                        "id": 0,
                        "polygon": {
                            "x0": 550,
                            "x1": 582,
                            "x2": 582,
                            "x3": 550,
                            "y0": 37,
                            "y1": 37,
                            "y2": 62,
                            "y3": 62
                        },
                        "text": "K_{to}"
                    },
                    {
                        "id": 1,
                        "polygon": {
                            "x0": 550,
                            "x1": 562,
                            "x2": 562,
                            "x3": 550,
                            "y0": 65,
                            "y1": 65,
                            "y2": 85,
                            "y3": 85
                        },
                        "text": "3"
                    },
                    {
                        "id": 2,
                        "polygon": {
                            "x0": 550,
                            "x1": 581,
                            "x2": 581,
                            "x3": 550,
                            "y0": 95,
                            "y1": 95,
                            "y2": 115,
                            "y3": 115
                        },
                        "text": "2.8"
                    },
                    {
                        "id": 3,
                        "polygon": {
                            "x0": 550,
                            "x1": 580,
                            "x2": 580,
                            "x3": 550,
                            "y0": 126,
                            "y1": 126,
                            "y2": 146,
                            "y3": 146
                        },
                        "text": "2.5"
                    },
                    {
                        "id": 4,
                        "polygon": {
                            "x0": 663,
                            "x1": 692,
                            "x2": 692,
                            "x3": 663,
                            "y0": 380,
                            "y1": 380,
                            "y2": 400,
                            "y3": 400
                        },
                        "text": "0.5"
                    },
                    {
                        "id": 5,
                        "polygon": {
                            "x0": 551,
                            "x1": 581,
                            "x2": 581,
                            "x3": 551,
                            "y0": 380,
                            "y1": 380,
                            "y2": 400,
                            "y3": 400
                        },
                        "text": "0.4"
                    },
                    {
                        "id": 6,
                        "polygon": {
                            "x0": 440,
                            "x1": 470,
                            "x2": 470,
                            "x3": 440,
                            "y0": 380,
                            "y1": 380,
                            "y2": 400,
                            "y3": 400
                        },
                        "text": "0.3"
                    },
                    {
                        "id": 7,
                        "polygon": {
                            "x0": 328,
                            "x1": 358,
                            "x2": 358,
                            "x3": 328,
                            "y0": 380,
                            "y1": 380,
                            "y2": 400,
                            "y3": 400
                        },
                        "text": "0.2"
                    },
                    {
                        "id": 8,
                        "polygon": {
                            "x0": 217,
                            "x1": 245,
                            "x2": 245,
                            "x3": 217,
                            "y0": 380,
                            "y1": 380,
                            "y2": 400,
                            "y3": 400
                        },
                        "text": "0.1"
                    },
                    {
                        "id": 9,
                        "polygon": {
                            "x0": 63,
                            "x1": 94,
                            "x2": 94,
                            "x3": 63,
                            "y0": 344,
                            "y1": 344,
                            "y2": 364,
                            "y3": 364
                        },
                        "text": "0.0"
                    },
                    {
                        "id": 10,
                        "polygon": {
                            "x0": 63,
                            "x1": 95,
                            "x2": 95,
                            "x3": 63,
                            "y0": 3,
                            "y1": 3,
                            "y2": 21,
                            "y3": 21
                        },
                        "text": "4.0"
                    },
                    {
                        "id": 11,
                        "polygon": {
                            "x0": 63,
                            "x1": 93,
                            "x2": 93,
                            "x3": 63,
                            "y0": 87,
                            "y1": 87,
                            "y2": 107,
                            "y3": 107
                        },
                        "text": "3.0"
                    },
                    {
                        "id": 12,
                        "polygon": {
                            "x0": 63,
                            "x1": 95,
                            "x2": 95,
                            "x3": 63,
                            "y0": 173,
                            "y1": 173,
                            "y2": 193,
                            "y3": 193
                        },
                        "text": "2.0"
                    },
                    {
                        "id": 13,
                        "polygon": {
                            "x0": 67,
                            "x1": 95,
                            "x2": 95,
                            "x3": 67,
                            "y0": 258,
                            "y1": 258,
                            "y2": 278,
                            "y3": 278
                        },
                        "text": "1.0"
                    },
                    {
                        "id": 14,
                        "polygon": {
                            "x0": 115,
                            "x1": 128,
                            "x2": 128,
                            "x3": 115,
                            "y0": 380,
                            "y1": 380,
                            "y2": 400,
                            "y3": 400
                        },
                        "text": "0"
                    },
                    {
                        "id": 15,
                        "polygon": {
                            "x0": 364,
                            "x1": 437,
                            "x2": 437,
                            "x3": 364,
                            "y0": 423,
                            "y1": 423,
                            "y2": 452,
                            "y3": 452
                        },
                        "text": "S_{h}/2S_{c}"
                    },
                    {
                        "id": 16,
                        "polygon": {
                            "x0": 3,
                            "x1": 34,
                            "x2": 34,
                            "x3": 3,
                            "y0": 25,
                            "y1": 25,
                            "y2": 346,
                            "y3": 346
                        },
                        "text": "NC(\\Delta\\sigma)^{3}/ (a_i^0.5 - a_f^-0.5) (10^{-2})"
                    }
                ]
            }
        },
        "name": "Axes Analysis",
        "output": {
            "_plot_bb": {
                "height": 342,
                "width": 560,
                "x0": 119,
                "y0": 13
            },
            "axes": {
                "_x-tick-type": "markers",
                "_x2-tick-type": null,
                "_y-tick-type": "markers",
                "_y2-tick-type": null,
                "x-axis": [
                    {
                        "id": 14,
                        "tick_pt": {
                            "x": 119,
                            "y": 355
                        }
                    },
                    {
                        "id": 8,
                        "tick_pt": {
                            "x": 231,
                            "y": 355
                        }
                    },
                    {
                        "id": 7,
                        "tick_pt": {
                            "x": 343,
                            "y": 355
                        }
                    },
                    {
                        "id": 6,
                        "tick_pt": {
                            "x": 455,
                            "y": 355
                        }
                    },
                    {
                        "id": 5,
                        "tick_pt": {
                            "x": 568,
                            "y": 355
                        }
                    },
                    {
                        "id": 4,
                        "tick_pt": {
                            "x": 680,
                            "y": 355
                        }
                    }
                ],
                "x-axis-2": [],
                "y-axis": [
                    {
                        "id": 10,
                        "tick_pt": {
                            "x": 119,
                            "y": 13
                        }
                    },
                    {
                        "id": 11,
                        "tick_pt": {
                            "x": 119,
                            "y": 99
                        }
                    },
                    {
                        "id": 12,
                        "tick_pt": {
                            "x": 119,
                            "y": 184
                        }
                    },
                    {
                        "id": 13,
                        "tick_pt": {
                            "x": 119,
                            "y": 269
                        }
                    },
                    {
                        "id": 9,
                        "tick_pt": {
                            "x": 119,
                            "y": 355
                        }
                    }
                ],
                "y-axis-2": []
            }
        }
    },
    "task5": {
        "input": {
            "task1_output": {
                "chart_type": "line"
            },
            "task2_output": {
                "text_blocks": [
                    {
                        "id": 0,
                        "polygon": {
                            "x0": 550,
                            "x1": 582,
                            "x2": 582,
                            "x3": 550,
                            "y0": 37,
                            "y1": 37,
                            "y2": 62,
                            "y3": 62
                        },
                        "text": "K_{to}"
                    },
                    {
                        "id": 1,
                        "polygon": {
                            "x0": 550,
                            "x1": 562,
                            "x2": 562,
                            "x3": 550,
                            "y0": 65,
                            "y1": 65,
                            "y2": 85,
                            "y3": 85
                        },
                        "text": "3"
                    },
                    {
                        "id": 2,
                        "polygon": {
                            "x0": 550,
                            "x1": 581,
                            "x2": 581,
                            "x3": 550,
                            "y0": 95,
                            "y1": 95,
                            "y2": 115,
                            "y3": 115
                        },
                        "text": "2.8"
                    },
                    {
                        "id": 3,
                        "polygon": {
                            "x0": 550,
                            "x1": 580,
                            "x2": 580,
                            "x3": 550,
                            "y0": 126,
                            "y1": 126,
                            "y2": 146,
                            "y3": 146
                        },
                        "text": "2.5"
                    },
                    {
                        "id": 4,
                        "polygon": {
                            "x0": 663,
                            "x1": 692,
                            "x2": 692,
                            "x3": 663,
                            "y0": 380,
                            "y1": 380,
                            "y2": 400,
                            "y3": 400
                        },
                        "text": "0.5"
                    },
                    {
                        "id": 5,
                        "polygon": {
                            "x0": 551,
                            "x1": 581,
                            "x2": 581,
                            "x3": 551,
                            "y0": 380,
                            "y1": 380,
                            "y2": 400,
                            "y3": 400
                        },
                        "text": "0.4"
                    },
                    {
                        "id": 6,
                        "polygon": {
                            "x0": 440,
                            "x1": 470,
                            "x2": 470,
                            "x3": 440,
                            "y0": 380,
                            "y1": 380,
                            "y2": 400,
                            "y3": 400
                        },
                        "text": "0.3"
                    },
                    {
                        "id": 7,
                        "polygon": {
                            "x0": 328,
                            "x1": 358,
                            "x2": 358,
                            "x3": 328,
                            "y0": 380,
                            "y1": 380,
                            "y2": 400,
                            "y3": 400
                        },
                        "text": "0.2"
                    },
                    {
                        "id": 8,
                        "polygon": {
                            "x0": 217,
                            "x1": 245,
                            "x2": 245,
                            "x3": 217,
                            "y0": 380,
                            "y1": 380,
                            "y2": 400,
                            "y3": 400
                        },
                        "text": "0.1"
                    },
                    {
                        "id": 9,
                        "polygon": {
                            "x0": 63,
                            "x1": 94,
                            "x2": 94,
                            "x3": 63,
                            "y0": 344,
                            "y1": 344,
                            "y2": 364,
                            "y3": 364
                        },
                        "text": "0.0"
                    },
                    {
                        "id": 10,
                        "polygon": {
                            "x0": 63,
                            "x1": 95,
                            "x2": 95,
                            "x3": 63,
                            "y0": 3,
                            "y1": 3,
                            "y2": 21,
                            "y3": 21
                        },
                        "text": "4.0"
                    },
                    {
                        "id": 11,
                        "polygon": {
                            "x0": 63,
                            "x1": 93,
                            "x2": 93,
                            "x3": 63,
                            "y0": 87,
                            "y1": 87,
                            "y2": 107,
                            "y3": 107
                        },
                        "text": "3.0"
                    },
                    {
                        "id": 12,
                        "polygon": {
                            "x0": 63,
                            "x1": 95,
                            "x2": 95,
                            "x3": 63,
                            "y0": 173,
                            "y1": 173,
                            "y2": 193,
                            "y3": 193
                        },
                        "text": "2.0"
                    },
                    {
                        "id": 13,
                        "polygon": {
                            "x0": 67,
                            "x1": 95,
                            "x2": 95,
                            "x3": 67,
                            "y0": 258,
                            "y1": 258,
                            "y2": 278,
                            "y3": 278
                        },
                        "text": "1.0"
                    },
                    {
                        "id": 14,
                        "polygon": {
                            "x0": 115,
                            "x1": 128,
                            "x2": 128,
                            "x3": 115,
                            "y0": 380,
                            "y1": 380,
                            "y2": 400,
                            "y3": 400
                        },
                        "text": "0"
                    },
                    {
                        "id": 15,
                        "polygon": {
                            "x0": 364,
                            "x1": 437,
                            "x2": 437,
                            "x3": 364,
                            "y0": 423,
                            "y1": 423,
                            "y2": 452,
                            "y3": 452
                        },
                        "text": "S_{h}/2S_{c}"
                    },
                    {
                        "id": 16,
                        "polygon": {
                            "x0": 3,
                            "x1": 34,
                            "x2": 34,
                            "x3": 3,
                            "y0": 25,
                            "y1": 25,
                            "y2": 346,
                            "y3": 346
                        },
                        "text": "NC(\\Delta\\sigma)^{3}/ (a_i^0.5 - a_f^-0.5) (10^{-2})"
                    }
                ]
            }
        },
        "name": "Legend Analysis",
        "output": {
            "legend_pairs": [
                {
                    "bb": {
                        "height": 15,
                        "width": 60,
                        "x0": 485,
                        "y0": 65
                    },
                    "id": 1
                },
                {
                    "bb": {
                        "height": 15,
                        "width": 60,
                        "x0": 487,
                        "y0": 98
                    },
                    "id": 2
                },
                {
                    "bb": {
                        "height": 15,
                        "width": 60,
                        "x0": 487,
                        "y0": 131
                    },
                    "id": 3
                }
            ]
        }
    },
    "task6": {
        "input": {
            "task1_output": {
                "chart_type": "line"
            },
            "task2_output": {
                "text_blocks": [
                    {
                        "id": 0,
                        "polygon": {
                            "x0": 550,
                            "x1": 582,
                            "x2": 582,
                            "x3": 550,
                            "y0": 37,
                            "y1": 37,
                            "y2": 62,
                            "y3": 62
                        },
                        "text": "K_{to}"
                    },
                    {
                        "id": 1,
                        "polygon": {
                            "x0": 550,
                            "x1": 562,
                            "x2": 562,
                            "x3": 550,
                            "y0": 65,
                            "y1": 65,
                            "y2": 85,
                            "y3": 85
                        },
                        "text": "3"
                    },
                    {
                        "id": 2,
                        "polygon": {
                            "x0": 550,
                            "x1": 581,
                            "x2": 581,
                            "x3": 550,
                            "y0": 95,
                            "y1": 95,
                            "y2": 115,
                            "y3": 115
                        },
                        "text": "2.8"
                    },
                    {
                        "id": 3,
                        "polygon": {
                            "x0": 550,
                            "x1": 580,
                            "x2": 580,
                            "x3": 550,
                            "y0": 126,
                            "y1": 126,
                            "y2": 146,
                            "y3": 146
                        },
                        "text": "2.5"
                    },
                    {
                        "id": 4,
                        "polygon": {
                            "x0": 663,
                            "x1": 692,
                            "x2": 692,
                            "x3": 663,
                            "y0": 380,
                            "y1": 380,
                            "y2": 400,
                            "y3": 400
                        },
                        "text": "0.5"
                    },
                    {
                        "id": 5,
                        "polygon": {
                            "x0": 551,
                            "x1": 581,
                            "x2": 581,
                            "x3": 551,
                            "y0": 380,
                            "y1": 380,
                            "y2": 400,
                            "y3": 400
                        },
                        "text": "0.4"
                    },
                    {
                        "id": 6,
                        "polygon": {
                            "x0": 440,
                            "x1": 470,
                            "x2": 470,
                            "x3": 440,
                            "y0": 380,
                            "y1": 380,
                            "y2": 400,
                            "y3": 400
                        },
                        "text": "0.3"
                    },
                    {
                        "id": 7,
                        "polygon": {
                            "x0": 328,
                            "x1": 358,
                            "x2": 358,
                            "x3": 328,
                            "y0": 380,
                            "y1": 380,
                            "y2": 400,
                            "y3": 400
                        },
                        "text": "0.2"
                    },
                    {
                        "id": 8,
                        "polygon": {
                            "x0": 217,
                            "x1": 245,
                            "x2": 245,
                            "x3": 217,
                            "y0": 380,
                            "y1": 380,
                            "y2": 400,
                            "y3": 400
                        },
                        "text": "0.1"
                    },
                    {
                        "id": 9,
                        "polygon": {
                            "x0": 63,
                            "x1": 94,
                            "x2": 94,
                            "x3": 63,
                            "y0": 344,
                            "y1": 344,
                            "y2": 364,
                            "y3": 364
                        },
                        "text": "0.0"
                    },
                    {
                        "id": 10,
                        "polygon": {
                            "x0": 63,
                            "x1": 95,
                            "x2": 95,
                            "x3": 63,
                            "y0": 3,
                            "y1": 3,
                            "y2": 21,
                            "y3": 21
                        },
                        "text": "4.0"
                    },
                    {
                        "id": 11,
                        "polygon": {
                            "x0": 63,
                            "x1": 93,
                            "x2": 93,
                            "x3": 63,
                            "y0": 87,
                            "y1": 87,
                            "y2": 107,
                            "y3": 107
                        },
                        "text": "3.0"
                    },
                    {
                        "id": 12,
                        "polygon": {
                            "x0": 63,
                            "x1": 95,
                            "x2": 95,
                            "x3": 63,
                            "y0": 173,
                            "y1": 173,
                            "y2": 193,
                            "y3": 193
                        },
                        "text": "2.0"
                    },
                    {
                        "id": 13,
                        "polygon": {
                            "x0": 67,
                            "x1": 95,
                            "x2": 95,
                            "x3": 67,
                            "y0": 258,
                            "y1": 258,
                            "y2": 278,
                            "y3": 278
                        },
                        "text": "1.0"
                    },
                    {
                        "id": 14,
                        "polygon": {
                            "x0": 115,
                            "x1": 128,
                            "x2": 128,
                            "x3": 115,
                            "y0": 380,
                            "y1": 380,
                            "y2": 400,
                            "y3": 400
                        },
                        "text": "0"
                    },
                    {
                        "id": 15,
                        "polygon": {
                            "x0": 364,
                            "x1": 437,
                            "x2": 437,
                            "x3": 364,
                            "y0": 423,
                            "y1": 423,
                            "y2": 452,
                            "y3": 452
                        },
                        "text": "S_{h}/2S_{c}"
                    },
                    {
                        "id": 16,
                        "polygon": {
                            "x0": 3,
                            "x1": 34,
                            "x2": 34,
                            "x3": 3,
                            "y0": 25,
                            "y1": 25,
                            "y2": 346,
                            "y3": 346
                        },
                        "text": "NC(\\Delta\\sigma)^{3}/ (a_i^0.5 - a_f^-0.5) (10^{-2})"
                    }
                ]
            },
            "task3_output": {
                "text_roles": [
                    {
                        "id": 0,
                        "role": "legend_title"
                    },
                    {
                        "id": 1,
                        "role": "legend_label"
                    },
                    {
                        "id": 2,
                        "role": "legend_label"
                    },
                    {
                        "id": 3,
                        "role": "legend_label"
                    },
                    {
                        "id": 4,
                        "role": "tick_label"
                    },
                    {
                        "id": 5,
                        "role": "tick_label"
                    },
                    {
                        "id": 6,
                        "role": "tick_label"
                    },
                    {
                        "id": 7,
                        "role": "tick_label"
                    },
                    {
                        "id": 8,
                        "role": "tick_label"
                    },
                    {
                        "id": 9,
                        "role": "tick_label"
                    },
                    {
                        "id": 10,
                        "role": "tick_label"
                    },
                    {
                        "id": 11,
                        "role": "tick_label"
                    },
                    {
                        "id": 12,
                        "role": "tick_label"
                    },
                    {
                        "id": 13,
                        "role": "tick_label"
                    },
                    {
                        "id": 14,
                        "role": "tick_label"
                    },
                    {
                        "id": 15,
                        "role": "axis_title"
                    },
                    {
                        "id": 16,
                        "role": "axis_title"
                    }
                ]
            },
            "task4_output": {
                "_plot_bb": {
                    "height": 342,
                    "width": 560,
                    "x0": 119,
                    "y0": 13
                },
                "axes": {
                    "_x-tick-type": "markers",
                    "_x2-tick-type": null,
                    "_y-tick-type": "markers",
                    "_y2-tick-type": null,
                    "x-axis": [
                        {
                            "id": 14,
                            "tick_pt": {
                                "x": 119,
                                "y": 355
                            }
                        },
                        {
                            "id": 8,
                            "tick_pt": {
                                "x": 231,
                                "y": 355
                            }
                        },
                        {
                            "id": 7,
                            "tick_pt": {
                                "x": 343,
                                "y": 355
                            }
                        },
                        {
                            "id": 6,
                            "tick_pt": {
                                "x": 455,
                                "y": 355
                            }
                        },
                        {
                            "id": 5,
                            "tick_pt": {
                                "x": 568,
                                "y": 355
                            }
                        },
                        {
                            "id": 4,
                            "tick_pt": {
                                "x": 680,
                                "y": 355
                            }
                        }
                    ],
                    "x-axis-2": [],
                    "y-axis": [
                        {
                            "id": 10,
                            "tick_pt": {
                                "x": 119,
                                "y": 13
                            }
                        },
                        {
                            "id": 11,
                            "tick_pt": {
                                "x": 119,
                                "y": 99
                            }
                        },
                        {
                            "id": 12,
                            "tick_pt": {
                                "x": 119,
                                "y": 184
                            }
                        },
                        {
                            "id": 13,
                            "tick_pt": {
                                "x": 119,
                                "y": 269
                            }
                        },
                        {
                            "id": 9,
                            "tick_pt": {
                                "x": 119,
                                "y": 355
                            }
                        }
                    ],
                    "y-axis-2": []
                }
            },
            "task5_output": {
                "legend_pairs": [
                    {
                        "bb": {
                            "height": 15,
                            "width": 60,
                            "x0": 485,
                            "y0": 65
                        },
                        "id": 1
                    },
                    {
                        "bb": {
                            "height": 15,
                            "width": 60,
                            "x0": 487,
                            "y0": 98
                        },
                        "id": 2
                    },
                    {
                        "bb": {
                            "height": 15,
                            "width": 60,
                            "x0": 487,
                            "y0": 131
                        },
                        "id": 3
                    }
                ]
            }
        },
        "name": "Data Extraction",
        "output": {
            "data series": [
                {
                    "data": [
                        {
                            "x": 0.004462559128908471,
                            "y": 2.093890298653133
                        },
                        {
                            "x": 0.030642906018504768,
                            "y": 1.800507515127854
                        },
                        {
                            "x": 0.0603933002112278,
                            "y": 1.5116142885028296
                        },
                        {
                            "x": 0.10085383631333114,
                            "y": 1.2305289869217246
                        },
                        {
                            "x": 0.15975961681492284,
                            "y": 0.886980284989263
                        },
                        {
                            "x": 0.23116056287745818,
                            "y": 0.6605504587155955
                        },
                        {
                            "x": 0.29899146163686674,
                            "y": 0.5121998828811232
                        },
                        {
                            "x": 0.40252283342754286,
                            "y": 0.363849307046651
                        },
                        {
                            "x": 0.5001041263796744,
                            "y": 0.25902791333203146
                        }
                    ],
                    "name": "3"
                },
                {
                    "data": [
                        {
                            "x": 0.0038675512450540056,
                            "y": 2.584813585789576
                        },
                        {
                            "x": 0.031237913902359193,
                            "y": 2.1830958422799136
                        },
                        {
                            "x": 0.059798292327373326,
                            "y": 1.8239312902596128
                        },
                        {
                            "x": 0.09906881266176776,
                            "y": 1.4881905133710713
                        },
                        {
                            "x": 0.15975961681492284,
                            "y": 1.1056021862190115
                        },
                        {
                            "x": 0.2287805313420403,
                            "y": 0.8245168846379066
                        },
                        {
                            "x": 0.3007764852884301,
                            "y": 0.6058949834081582
                        },
                        {
                            "x": 0.39776277035670726,
                            "y": 0.44973648252976683
                        },
                        {
                            "x": 0.5001041263796744,
                            "y": 0.31270739800897834
                        }
                    ],
                    "name": "2.8"
                },
                {
                    "data": [
                        {
                            "x": 0.0020825275934906223,
                            "y": 3.6379074760882295
                        },
                        {
                            "x": 0.03004789813465029,
                            "y": 3.0888151473745844
                        },
                        {
                            "x": 0.059798292327373326,
                            "y": 2.5734920944758928
                        },
                        {
                            "x": 0.09787879689405886,
                            "y": 2.0972086667967984
                        },
                        {
                            "x": 0.15797459316335946,
                            "y": 1.5662697638102667
                        },
                        {
                            "x": 0.23116056287745818,
                            "y": 1.1368338863946894
                        },
                        {
                            "x": 0.29899146163686674,
                            "y": 0.8713644349014241
                        },
                        {
                            "x": 0.39716776247285274,
                            "y": 0.613702908452078
                        },
                        {
                            "x": 0.49950911849582,
                            "y": 0.4288502830372823
                        }
                    ],
                    "name": "2.5"
                }
            ],
            "visual elements": {
                "bars": [],
                "boxplots": [],
                "lines": [
                    [
                        {
                            "x": 124.33333333333334,
                            "y": 176.08333333333334
                        },
                        {
                            "x": 153.66666666666669,
                            "y": 201.13333333333338
                        },
                        {
                            "x": 187.0,
                            "y": 225.80000000000004
                        },
                        {
                            "x": 232.33333333333331,
                            "y": 249.80000000000004
                        },
                        {
                            "x": 298.33333333333337,
                            "y": 279.1333333333334
                        },
                        {
                            "x": 378.33333333333337,
                            "y": 298.4666666666667
                        },
                        {
                            "x": 454.33333333333337,
                            "y": 311.1333333333334
                        },
                        {
                            "x": 570.3333333333333,
                            "y": 323.80000000000007
                        },
                        {
                            "x": 679.6666666666666,
                            "y": 332.75
                        }
                    ],
                    [
                        {
                            "x": 123.66666666666667,
                            "y": 134.16666666666669
                        },
                        {
                            "x": 154.33333333333331,
                            "y": 168.4666666666667
                        },
                        {
                            "x": 186.33333333333331,
                            "y": 199.13333333333338
                        },
                        {
                            "x": 230.33333333333331,
                            "y": 227.8
                        },
                        {
                            "x": 298.33333333333337,
                            "y": 260.4666666666667
                        },
                        {
                            "x": 375.6666666666667,
                            "y": 284.4666666666667
                        },
                        {
                            "x": 456.33333333333337,
                            "y": 303.1333333333334
                        },
                        {
                            "x": 565.0,
                            "y": 316.4666666666667
                        },
                        {
                            "x": 679.6666666666666,
                            "y": 328.1666666666667
                        }
                    ],
                    [
                        {
                            "x": 121.66666666666667,
                            "y": 44.25
                        },
                        {
                            "x": 153.0,
                            "y": 91.13333333333338
                        },
                        {
                            "x": 186.33333333333331,
                            "y": 135.13333333333335
                        },
                        {
                            "x": 229.0,
                            "y": 175.8
                        },
                        {
                            "x": 296.33333333333337,
                            "y": 221.13333333333338
                        },
                        {
                            "x": 378.33333333333337,
                            "y": 257.80000000000007
                        },
                        {
                            "x": 454.33333333333337,
                            "y": 280.4666666666667
                        },
                        {
                            "x": 564.3333333333333,
                            "y": 302.4666666666667
                        },
                        {
                            "x": 679.0,
                            "y": 318.25
                        }
                    ]
                ],
                "scatter points": []
            }
        }
    }
}